{
  "kind": "collectionType",
  "collectionName": "menyu_na_nedelyus",
  "info": {
    "singularName": "menyu-na-nedelyu",
    "pluralName": "menyu-na-nedelyus",
    "displayName": "Меню на неделю"
  },
  "options": {
    "draftAndPublish": true
  },
  "pluginOptions": {},
  "attributes": {
    "monday": {
      "allowedTypes": [
        "images",
        "files",
        "videos",
        "audios"
      ],
      "type": "media",
      "multiple": false
    },
    "tuesday": {
      "allowedTypes": [
        "images",
        "files",
        "videos",
        "audios"
      ],
      "type": "media",
      "multiple": false
    },
    "wednesday": {
      "allowedTypes": [
        "images",
        "files",
        "videos",
        "audios"
      ],
      "type": "media",
      "multiple": false
    },
    "thursday": {
      "allowedTypes": [
        "images",
        "files",
        "videos",
        "audios"
      ],
      "type": "media",
      "multiple": false
    },
    "friday": {
      "allowedTypes": [
        "images",
        "files",
        "videos",
        "audios"
      ],
      "type": "media",
      "multiple": false
    }
  }
}
